{"cameraMode":{"drawMode":0,"name":"Shaded","section":"Shading Mode"},"sceneLighting":true,"audioPlay":false,"sceneViewState":{"m_AlwaysRefresh":false,"showFog":true,"showSkybox":true,"showFlares":true,"showImageEffects":true,"showParticleSystems":true,"showVisualEffectGraphs":true,"m_FxEnabled":true},"in2DMode":false,"pivot":{"x":78.4766845703125,"y":100.86216735839844,"z":113.91593170166016},"rotation":{"x":-0.504146933555603,"y":-0.49698570370674136,"z":0.4801441431045532,"w":-0.5185753703117371},"size":1.5461727380752564,"orthographic":false}